jupytercon/.__init__.py.swp
jupytercon/.__init__.py.un~
jupytercon/__init__.py
jupytercon-0.0.1.dist-info/LICENSE
jupytercon-0.0.1.dist-info/WHEEL
jupytercon-0.0.1.dist-info/METADATA
jupytercon-0.0.1.dist-info/RECORD
