Metadata-Version: 1.2
Name: jupytercon
Version: 0.0.1
Summary: place holder for JupyterCon
Home-page: https://github.com/Carreau/jupytercon
License: UNKNOWN
Author: Matthias Bussonnier
Author-email: bussonniermatthias@gmail.com
Classifier: License :: OSI Approved :: MIT License
